Workbook

Sheet README
A1: AlarmX — Unit Economics Model
A3: What this answers
A4: How much cash AlarmX can pay a single user per month without losing money.
A5: Everything else in the product spec depends on that one number.
A7: How to use it
A8: 1. Open the Assumptions tab. Edit ONLY the blue cells.
A9: 2. Three scenario columns: Conservative / Base / Optimistic. Base is the planning case.
A10: 3. The Model tab computes the sustainable earning cap for each scenario. Nothing there is typed by hand.
A11: 4. The Scale tab shows monthly P&L at 10k / 100k / 1M MAU. Set your chosen cap in the yellow cell.
A12: 5. The Sensitivity tab shows contribution per user across a grid of caps and revenue levels.
A14: Colour key
A15: Blue text = hardcoded input you can edit
... A33: for a new app with no traffic history. Read that column before setting the cap.

Sheet Assumptions
A1: Assumptions — edit the blue cells only
A3: Input | B3: Conservative | C3: Base | D3: Optimistic | E3: Unit | F3: Source / note
A4: GLOBAL
A5: USD / INR exchange rate | B5: 88 | C5: 88 | D5: 88 | E5: ₹ per $ | F5: Assumption, 2026
A6: Active days per user per month | B6: 20 | C6: 26 | D6: 30 | E6: days | F6: Days the user opens the app and completes an alarm
A7: AD REVENUE
A8: Rewarded video eCPM | B8: 1 | C8: 1.5 | D8: 2.5 | E8: $ per 1,000 | F8: India Android rewarded ~$1.50; India range $0.50–$2.00
A9: Rewarded videos per active day | B9: 2 | C9: 3 | D9: 4 | E9: views | F9: Assumption — how many the user will actually sit through
A10: Ad fill rate | B10: 0.7 | C10: 0.8 | D10: 0.9 | E10: % | F10: Share of ad requests that return a paying ad in India
A11: Interstitial eCPM | B11: 0.25 | C11: 0.4 | D11: 0.7 | E11: $ per 1,000 | F11: Materially below rewarded video
A12: Interstitials per active day | B12: 3 | C12: 4 | D12: 6 | E12: views | F12: Assumption
A13: Banner revenue | B13: 1 | C13: 2 | D13: 4 | E13: ₹/user/month | F13: Assumption — banners earn very little in India
A14: SURVEY DATA RESALE
A15: One-time profile resale value | B15: 8 | C15: 15 | D15: 30 | E15: ₹ per user | F15: PLACEHOLDER — validate with a real buyer
A16: Expected user lifetime | B16: 3 | C16: 4 | D16: 6 | E16: months | F16: Used to amortise the one-time value
A17: Daily drip batch value | B17: 0.15 | C17: 0.25 | D17: 0.5 | E17: ₹ per batch | F17: PLACEHOLDER — 2–3 questions answered per day
A18: SPONSORED QR — DORMANT TODAY
A19: Sponsored scans per active day | B19: 0 | C19: 0 | D19: 0 | E19: scans | F19: ZERO until a brand partnership signs. Rails built, switch off.
A20: Brand-funded value per scan | B20: 0.5 | C20: 1 | D20: 2 | E20: ₹ per scan | F20: For scenario testing only — no revenue until row 19 > 0
A21: COSTS
A22: UPI payout fee | B22: 5 | C22: 3 | D22: 2 | E22: ₹ per payout | F22: RazorpayX ₹2–5 per payout; UPI at the low end
A23: Payouts per withdrawing user | B23: 1 | C23: 1 | D23: 1 | E23: per month | F23: Monthly batch payout keeps this at 1
A24: Breakage — earned but never withdrawn | B24: 0.25 | C24: 0.4 | D24: 0.55 | E24: % | F24: Users who churn below the ₹30 minimum. Real, and it matters a lot.
A25: Infrastructure cost | B25: 0.8 | C25: 0.5 | D25: 0.3 | E25: ₹/MAU/month | F25: Firebase, Firestore, Cloud Functions, Play Integrity
A26: SMS / OTP cost | B26: 0.3 | C26: 0.15 | D26: 0.1 | E26: ₹/user/month | F26: Assumption
A27: Support cost | B27: 0.6 | C27: 0.3 | D27: 0.15 | E27: ₹/user/month | F27: Withdrawal disputes dominate this line
A28: Fraud leakage | B28: 0.1 | C28: 0.05 | D28: 0.02 | E28: % of rewards | F28: Rupees paid to accounts that beat the fraud controls
A29: TARGETS
A30: Target contribution margin | B30: 0.3 | C30: 0.3 | D30: 0.3 | E30: % of revenue | F30: Profit retained before the reward budget is set
A31: Minimum withdrawal threshold | B31: 30 | C31: 30 | D31: 30 | E31: ₹ | F31: Product decision — drives the breakage rate above

Sheet Model
A1: Per-user monthly economics and the sustainable earning cap
A2: Every figure below is per active user per month. Nothing here is typed by hand.
A4: Line item | B4: Conservative | C4: Base | D4: Optimistic | E4: Note
A5: REVENUE
A6: Rewarded video | B6: =Assumptions!B8*Assumptions!B5/1000*Assumptions!B9*Assumptions!B6*Assumptions!B10 -> 2.464 | C6: =Assumptions!C8*Assumptions!C5/1000*Assumptions!C9*Assumptions!C6*Assumptions!C10 -> 8.2368 | D6: =Assumptions!D8*Assumptions!D5/1000*Assumptions!D9*Assumptions!D6*Assumptions!D10 -> 23.76 | E6: eCPM → ₹ per view × views/day × active days × fill rate
A7: Interstitial | B7: =Assumptions!B11*Assumptions!B5/1000*Assumptions!B12*Assumptions!B6*Assumptions!B10 -> 0.924 | C7: =Assumptions!C11*Assumptions!C5/1000*Assumptions!C12*Assumptions!C6*Assumptions!C10 -> 2.92864 | D7: =Assumptions!D11*Assumptions!D5/1000*Assumptions!D12*Assumptions!D6*Assumptions!D10 -> 9.9792
A8: Banner | B8: =Assumptions!B13 -> 1 | C8: =Assumptions!C13 -> 2 | D8: =Assumptions!D13 -> 4
A9: Survey — one-time profile, amortised | B9: =Assumptions!B15/Assumptions!B16 -> 2.6666667 | C9: =Assumptions!C15/Assumptions!C16 -> 3.75 | D9: =Assumptions!D15/Assumptions!D16 -> 5 | E9: One-time value spread over expected lifetime
A10: Survey — daily drip | B10: =Assumptions!B17*Assumptions!B6 -> 3 | C10: =Assumptions!C17*Assumptions!C6 -> 6.5 | D10: =Assumptions!D17*Assumptions!D6 -> 15 | E10: This is why the survey drips instead of dumping once
A11: Sponsored QR (dormant) | B11: =Assumptions!B19*Assumptions!B20*Assumptions!B6 -> 0 | C11: =Assumptions!C19*Assumptions!C20*Assumptions!C6 -> 0 | D11: =Assumptions!D19*Assumptions!D20*Assumptions!D6 -> 0 | E11: ₹0 until a brand signs
A12: TOTAL REVENUE | B12: =SUM(B6:B11) -> 10.054667 | C12: =SUM(C6:C11) -> 23.41544 | D12: =SUM(D6:D11) -> 57.7392
A14: NON-REWARD COSTS
A15: UPI payout fees | B15: =Assumptions!B22*Assumptions!B23*(1-Assumptions!B24) -> 3.75 | C15: =Assumptions!C22*Assumptions!C23*(1-Assumptions!C24) -> 1.8 | D15: =Assumptions!D22*Assumptions!D23*(1-Assumptions!D24) -> 0.9 | E15: Only non-breakage users ever trigger a payout
A16: Infrastructure | B16: =Assumptions!B25 -> 0.8 | C16: =Assumptions!C25 -> 0.5 | D16: =Assumptions!D25 -> 0.3
A17: SMS / OTP | B17: =Assumptions!B26 -> 0.3 | C17: =Assumptions!C26 -> 0.15 | D17: =Assumptions!D26 -> 0.1
A18: Support | B18: =Assumptions!B27 -> 0.6 | C18: =Assumptions!C27 -> 0.3 | D18: =Assumptions!D27 -> 0.15
A19: TOTAL NON-REWARD COST | B19: =SUM(B15:B18) -> 5.45 | C19: =SUM(C15:C18) -> 2.75 | D19: =SUM(D15:D18) -> 1.45
A21: REWARD BUDGET
A22: Target profit retained | B22: =B12*Assumptions!B30 -> 3.0164 | C22: =C12*Assumptions!C30 -> 7.024632 | D22: =D12*Assumptions!D30 -> 17.32176 | E22: Contribution margin held back before rewards
A23: Budget available for rewards | B23: =B12-B19-B22 -> 1.5882667 | C23: =C12-C19-C22 -> 13.640808 | D23: =D12-D19-D22 -> 38.96744 | E23: Revenue less non-reward cost less target profit
A24: Breakage factor | B24: =1-Assumptions!B24 -> 0.75 | C24: =1-Assumptions!C24 -> 0.6 | D24: =1-Assumptions!D24 -> 0.45 | E24: Share of accrued rewards actually paid out
A25: Fraud inflation factor | B25: =1+Assumptions!B28 -> 1.1 | C25: =1+Assumptions!C28 -> 1.05 | D25: =1+Assumptions!D28 -> 1.02 | E25: Rupees leaked to accounts that beat the controls
A26: SUSTAINABLE EARNING CAP | B26: =B23/(B24*B25) -> 1.9251717 | C26: =C23/(C24*C25) -> 21.652076 | D26: =D23/(D24*D25) -> 84.896383 | E26: Max a single user may accrue per month
A28: REALITY CHECK vs ORIGINAL DESIGN
A29: Original design cap (₹60 math + ₹30 streak + ₹5 signup) | B29: 95 | C29: 95 | D29: 95 | E29: The concept as originally specified
A30: Sustainable cap as % of original | B30: =B26/B29 -> 0.020264965 | C30: =C26/C29 -> 0.22791659 | D30: =D26/D29 -> 0.89364614 | E30: Below 100% means the original design pays out more than it earns
A31: Monthly loss per user at the original cap | B31: =B12-B19-(B29*B24*B25) -> -73.770333 | C31: =C12-C19-(C29*C24*C25) -> -39.18456 | D31: =D12-D19-(D29*D24*D25) -> 12.6842 | E31: Contribution per user if you shipped ₹95 unchanged

Sheet Scale
A1: Monthly P&L at scale — Base case
A2: Set the cap you intend to ship in the yellow cell. Compare against the sustainable cap on the Model tab.
A4: Earning cap to test | B4: 20 | C4: ₹ per user per month
A5: Sustainable cap (Base, from Model) | B5: =Model!C26 -> 21.652076 | C5: Ship at or below this number
A7: Line item | B7: 10k MAU | C7: 100k MAU | D7: 1M MAU
A8: Monthly active users | B8: 10000 | C8: 100000 | D8: 1000000
A9: Revenue | B9: =B8*Model!$C$12 -> 234154.4 | C9: =C8*Model!$C$12 -> 2341544 | D9: =D8*Model!$C$12 -> 23415440
A10: Non-reward costs | B10: =-B8*Model!$C$19 -> -27500 | C10: =-C8*Model!$C$19 -> -275000 | D10: =-D8*Model!$C$19 -> -2750000
A11: Reward payout at the tested cap | B11: =-B8*$B$4*Model!$C$24*Model!$C$25 -> -126000 | C11: =-C8*$B$4*Model!$C$24*Model!$C$25 -> -1260000 | D11: =-D8*$B$4*Model!$C$24*Model!$C$25 -> -12600000 | E11: Cap × share actually withdrawn × fraud inflation
A12: CONTRIBUTION | B12: =SUM(B9:B11) -> 80654.4 | C12: =SUM(C9:C11) -> 806544 | D12: =SUM(D9:D11) -> 8065440
A13: Contribution margin | B13: =IF(B9=0,0,B12/B9) -> 0.34444965 | C13: =IF(C9=0,0,C12/C9) -> 0.34444965 | D13: =IF(D9=0,0,D12/D9) -> 0.34444965
A15: Contribution at the ORIGINAL ₹95 cap | B15: =B8*Model!$C$12-B8*Model!$C$19-B8*Model!$C$29*Model!$C$24*Model!$C$25 -> -391845.6 | C15: =C8*Model!$C$12-C8*Model!$C$19-C8*Model!$C$29*Model!$C$24*Model!$C$25 -> -3918456 | D15: =D8*Model!$C$12-D8*Model!$C$19-D8*Model!$C$29*Model!$C$24*Model!$C$25 -> -39184560 | E15: What shipping the original design would have cost per month

Sheet Sensitivity
A1: Contribution per user per month
A2: Rows = earning cap you ship. Columns = total revenue per active user. Base-case costs, breakage and fraud applied.
A3: Negative (in brackets) means you lose money on every active user at that combination.
A5: Cap \ Revenue per user | B5: 10 | C5: 15 | D5: 20 | E5: 25 | F5: 30 | G5: 35 | H5: 40 | I5: 50
A6: 5 | B6: =B$5-Model!$C$19-$A6*Model!$C$24*Model!$C$25 -> 4.1 | C6: =C$5-Model!$C$19-$A6*Model!$C$24*Model!$C$25 -> 9.1 | D6: =D$5-Model!$C$19-$A6*Model!$C$24*Model!$C$25 -> 14.1 | E6: =E$5-Model!$C$19-$A6*Model!$C$24*Model!$C$25 -> 19.1 | F6: =F$5-Model!$C$19-$A6*Model!$C$24*Model!$C$25 -> 24.1 | G6: =G$5-Model!$C$19-$A6*Model!$C$24*Model!$C$25 -> 29.1 | H6: =H$5-Model!$C$19-$A6*Model!$C$24*Model!$C$25 -> 34.1 | I6: =I$5-Model!$C$19-$A6*Model!$C$24*Model!$C$25 -> 44.1
A7: 10 | B7: =B$5-Model!$C$19-$A7*Model!$C$24*Model!$C$25 -> 0.95 | C7: =C$5-Model!$C$19-$A7*Model!$C$24*Model!$C$25 -> 5.95 | D7: =D$5-Model!$C$19-$A7*Model!$C$24*Model!$C$25 -> 10.95 | E7: =E$5-Model!$C$19-$A7*Model!$C$24*Model!$C$25 -> 15.95 | F7: =F$5-Model!$C$19-$A7*Model!$C$24*Model!$C$25 -> 20.95 | G7: =G$5-Model!$C$19-$A7*Model!$C$24*Model!$C$25 -> 25.95 | H7: =H$5-Model!$C$19-$A7*Model!$C$24*Model!$C$25 -> 30.95 | I7: =I$5-Model!$C$19-$A7*Model!$C$24*Model!$C$25 -> 40.95
A8: 15 | B8: =B$5-Model!$C$19-$A8*Model!$C$24*Model!$C$25 -> -2.2 | C8: =C$5-Model!$C$19-$A8*Model!$C$24*Model!$C$25 -> 2.8 | D8: =D$5-Model!$C$19-$A8*Model!$C$24*Model!$C$25 -> 7.8 | E8: =E$5-Model!$C$19-$A8*Model!$C$24*Model!$C$25 -> 12.8 | F8: =F$5-Model!$C$19-$A8*Model!$C$24*Model!$C$25 -> 17.8 | G8: =G$5-Model!$C$19-$A8*Model!$C$24*Model!$C$25 -> 22.8 | H8: =H$5-Model!$C$19-$A8*Model!$C$24*Model!$C$25 -> 27.8 | I8: =I$5-Model!$C$19-$A8*Model!$C$24*Model!$C$25 -> 37.8
A9: 20 | B9: =B$5-Model!$C$19-$A9*Model!$C$24*Model!$C$25 -> -5.35 | C9: =C$5-Model!$C$19-$A9*Model!$C$24*Model!$C$25 -> -0.35 | D9: =D$5-Model!$C$19-$A9*Model!$C$24*Model!$C$25 -> 4.65 | E9: =E$5-Model!$C$19-$A9*Model!$C$24*Model!$C$25 -> 9.65 | F9: =F$5-Model!$C$19-$A9*Model!$C$24*Model!$C$25 -> 14.65 | G9: =G$5-Model!$C$19-$A9*Model!$C$24*Model!$C$25 -> 19.65 | H9: =H$5-Model!$C$19-$A9*Model!$C$24*Model!$C$25 -> 24.65 | I9: =I$5-Model!$C$19-$A9*Model!$C$24*Model!$C$25 -> 34.65
A10: 25 | B10: =B$5-Model!$C$19-$A10*Model!$C$24*Model!$C$25 -> -8.5 | C10: =C$5-Model!$C$19-$A10*Model!$C$24*Model!$C$25 -> -3.5 | D10: =D$5-Model!$C$19-$A10*Model!$C$24*Model!$C$25 -> 1.5 | E10: =E$5-Model!$C$19-$A10*Model!$C$24*Model!$C$25 -> 6.5 | F10: =F$5-Model!$C$19-$A10*Model!$C$24*Model!$C$25 -> 11.5 | G10: =G$5-Model!$C$19-$A10*Model!$C$24*Model!$C$25 -> 16.5 | H10: =H$5-Model!$C$19-$A10*Model!$C$24*Model!$C$25 -> 21.5 | I10: =I$5-Model!$C$19-$A10*Model!$C$24*Model!$C$25 -> 31.5
A11: 30 | B11: =B$5-Model!$C$19-$A11*Model!$C$24*Model!$C$25 -> -11.65 | C11: =C$5-Model!$C$19-$A11*Model!$C$24*Model!$C$25 -> -6.65 | D11: =D$5-Model!$C$19-$A11*Model!$C$24*Model!$C$25 -> -1.65 | E11: =E$5-Model!$C$19-$A11*Model!$C$24*Model!$C$25 -> 3.35 | F11: =F$5-Model!$C$19-$A11*Model!$C$24*Model!$C$25 -> 8.35 | G11: =G$5-Model!$C$19-$A11*Model!$C$24*Model!$C$25 -> 13.35 | H11: =H$5-Model!$C$19-$A11*Model!$C$24*Model!$C$25 -> 18.35 | I11: =I$5-Model!$C$19-$A11*Model!$C$24*Model!$C$25 -> 28.35
A12: 40 | B12: =B$5-Model!$C$19-$A12*Model!$C$24*Model!$C$25 -> -17.95 | C12: =C$5-Model!$C$19-$A12*Model!$C$24*Model!$C$25 -> -12.95 | D12: =D$5-Model!$C$19-$A12*Model!$C$24*Model!$C$25 -> -7.95 | E12: =E$5-Model!$C$19-$A12*Model!$C$24*Model!$C$25 -> -2.95 | F12: =F$5-Model!$C$19-$A12*Model!$C$24*Model!$C$25 -> 2.05 | G12: =G$5-Model!$C$19-$A12*Model!$C$24*Model!$C$25 -> 7.05 | H12: =H$5-Model!$C$19-$A12*Model!$C$24*Model!$C$25 -> 12.05 | I12: =I$5-Model!$C$19-$A12*Model!$C$24*Model!$C$25 -> 22.05
A13: 60 | B13: =B$5-Model!$C$19-$A13*Model!$C$24*Model!$C$25 -> -30.55 | C13: =C$5-Model!$C$19-$A13*Model!$C$24*Model!$C$25 -> -25.55 | D13: =D$5-Model!$C$19-$A13*Model!$C$24*Model!$C$25 -> -20.55 | E13: =E$5-Model!$C$19-$A13*Model!$C$24*Model!$C$25 -> -15.55 | F13: =F$5-Model!$C$19-$A13*Model!$C$24*Model!$C$25 -> -10.55 | G13: =G$5-Model!$C$19-$A13*Model!$C$24*Model!$C$25 -> -5.55 | H13: =H$5-Model!$C$19-$A13*Model!$C$24*Model!$C$25 -> -0.55 | I13: =I$5-Model!$C$19-$A13*Model!$C$24*Model!$C$25 -> 9.45
A14: 95 | B14: =B$5-Model!$C$19-$A14*Model!$C$24*Model!$C$25 -> -52.6 | C14: =C$5-Model!$C$19-$A14*Model!$C$24*Model!$C$25 -> -47.6 | D14: =D$5-Model!$C$19-$A14*Model!$C$24*Model!$C$25 -> -42.6 | E14: =E$5-Model!$C$19-$A14*Model!$C$24*Model!$C$25 -> -37.6 | F14: =F$5-Model!$C$19-$A14*Model!$C$24*Model!$C$25 -> -32.6 | G14: =G$5-Model!$C$19-$A14*Model!$C$24*Model!$C$25 -> -27.6 | H14: =H$5-Model!$C$19-$A14*Model!$C$24*Model!$C$25 -> -22.6 | I14: =I$5-Model!$C$19-$A14*Model!$C$24*Model!$C$25 -> -12.6
A16: ₹95 row is the original design. Everything to the left of break-even on that row is a loss per user per month.
